<templateSet group="Ruby">
  <template name="db" value="binding.pry" description="Debug with pry" toReformat="false" toShortenFQNames="true">
    <context>
      <option name="HTML_TEXT" value="false" />
      <option name="HTML" value="false" />
      <option name="XSL_TEXT" value="false" />
      <option name="XML" value="false" />
      <option name="RUBY" value="true" />
      <option name="RHTML" value="false" />
      <option name="CSS_PROPERTY_VALUE" value="false" />
      <option name="CSS_DECLARATION_BLOCK" value="false" />
      <option name="CSS_RULESET_LIST" value="false" />
      <option name="CSS" value="false" />
      <option name="SQL" value="false" />
      <option name="JAVA_SCRIPT" value="false" />
      <option name="CoffeeScript" value="false" />
      <option name="HAML" value="false" />
      <option name="Slim" value="false" />
      <option name="OTHER" value="false" />
    </context>
  </template>
  <template name="pry" value="binding.pry" description="binding.pry (debugger)" toReformat="false" toShortenFQNames="true">
    <context>
      <option name="HTML_TEXT" value="false" />
      <option name="HTML" value="false" />
      <option name="XSL_TEXT" value="false" />
      <option name="XML" value="false" />
      <option name="RUBY" value="false" />
      <option name="RHTML" value="false" />
      <option name="CSS_PROPERTY_VALUE" value="false" />
      <option name="CSS_DECLARATION_BLOCK" value="false" />
      <option name="CSS_RULESET_LIST" value="false" />
      <option name="CSS" value="false" />
      <option name="SQL" value="false" />
      <option name="JAVA_SCRIPT" value="false" />
      <option name="CoffeeScript" value="false" />
      <option name="HAML" value="false" />
      <option name="Slim" value="false" />
      <option name="OTHER" value="false" />
    </context>
  </template>
  <template name="service" value="class $CLASS_NAME$&#10;  attr_reader :$VAR1$, :options&#10;&#10;  class &lt;&lt; self&#10;    private :new&#10;&#10;    def call($VAR1$, options = {})&#10;      new($VAR1$, options).call&#10;    end&#10;  end&#10;&#10;  def initialize($VAR1$, options)&#10;    @$VAR1$ = $VAR1$&#10;    @options = options&#10;  end&#10;&#10;  def call&#10;    # do something cool&#10;    $END$&#10;  end&#10;end&#10;" description="Create a basic Service class" toReformat="true" toShortenFQNames="true">
    <variable name="CLASS_NAME" expression="" defaultValue="" alwaysStopAt="true" />
    <variable name="VAR1" expression="" defaultValue="" alwaysStopAt="true" />
    <context>
      <option name="HTML_TEXT" value="false" />
      <option name="HTML" value="false" />
      <option name="XSL_TEXT" value="false" />
      <option name="XML" value="false" />
      <option name="RUBY" value="true" />
      <option name="RHTML" value="false" />
      <option name="CSS_PROPERTY_VALUE" value="false" />
      <option name="CSS_DECLARATION_BLOCK" value="false" />
      <option name="CSS_RULESET_LIST" value="false" />
      <option name="CSS" value="false" />
      <option name="SQL" value="false" />
      <option name="JAVA_SCRIPT" value="false" />
      <option name="CoffeeScript" value="false" />
      <option name="HAML" value="false" />
      <option name="Slim" value="false" />
      <option name="OTHER" value="false" />
    </context>
  </template>
  <template name="concern" value="require 'active_support/concern'&#10;&#10;module Concerns&#10;  module $CONCERN_NAME$&#10;    extend ActiveSupport::Concern&#10;  &#10;    included do&#10;      $END$&#10;    end&#10;    &#10;    module ClassMethods&#10;    end&#10;  end&#10;end" description="Create an ActiveSupport::Concern" toReformat="true" toShortenFQNames="true">
    <variable name="CONCERN_NAME" expression="" defaultValue="" alwaysStopAt="true" />
    <context>
      <option name="HTML_TEXT" value="false" />
      <option name="HTML" value="false" />
      <option name="XSL_TEXT" value="false" />
      <option name="XML" value="false" />
      <option name="RUBY" value="true" />
      <option name="RHTML" value="false" />
      <option name="CSS_PROPERTY_VALUE" value="false" />
      <option name="CSS_DECLARATION_BLOCK" value="false" />
      <option name="CSS_RULESET_LIST" value="false" />
      <option name="CSS" value="false" />
      <option name="SQL" value="false" />
      <option name="JAVA_SCRIPT" value="false" />
      <option name="CoffeeScript" value="false" />
      <option name="HAML" value="false" />
      <option name="Slim" value="false" />
      <option name="OTHER" value="false" />
    </context>
  </template>
</templateSet>